{
  "_class": "group",
  "booleanOperation": 0,
  "clippingMaskMode": 0,
  "do_objectID": "4B500ADC-9680-43AC-9159-085C0F683122",
  "exportOptions": {
    "_class": "exportOptions",
    "do_objectID": "08C5D1FB-9172-4570-8D63-46147C37F54E",
    "exportFormats": [
    ],
    "includedLayerIds": [
    ],
    "layerOptions": 0,
    "shouldTrim": false
  },
  "frame": {
    "_class": "rect",
    "constrainProportions": false,
    "do_objectID": "0BBA1655-4FB3-43B6-9E21-3CB7F53BB59E",
    "height": 31,
    "width": 48,
    "x": 551.75,
    "y": 347.5
  },
  "hasClickThrough": false,
  "hasClippingMask": false,
  "isFixedToViewport": false,
  "isFlippedHorizontal": false,
  "isFlippedVertical": false,
  "isLocked": false,
  "isVisible": true,
  "layerListExpandedType": 0,
  "layers": [
    {
      "class": "shapePath",
      "id": "3C4757DA-4401-4D00-B975-23D34BE5BE2D"
    },
    {
      "class": "shapePath",
      "id": "D0945042-46AB-483E-A31E-07597788DA4F"
    }
  ],
  "name": "Home Button",
  "nameIsFixed": true,
  "resizingConstraint": 63,
  "resizingType": 0,
  "rotation": 0,
  "shouldBreakMaskChain": false,
  "style": {
    "_class": "style",
    "blur": {
      "_class": "blur",
      "center": "{0.5, 0.5}",
      "do_objectID": "1496D29C-DA9B-458B-BCB9-490B4A1A63C5",
      "isEnabled": false,
      "motionAngle": 0,
      "radius": 2.5,
      "saturation": 1,
      "type": 0
    },
    "do_objectID": "9F00CC35-46B6-4250-B026-BB45B254D8B3",
    "endMarkerType": 0,
    "miterLimit": 10,
    "startMarkerType": 0,
    "windingRule": 1
  }
}