{
  "_class": "bitmap",
  "booleanOperation": 0,
  "clippingMask": "{{0, 0}, {1, 1}}",
  "clippingMaskMode": 0,
  "do_objectID": "785154F4-1ED4-470F-95BC-E3F1F7AE0DD6",
  "exportOptions": {
    "_class": "exportOptions",
    "do_objectID": "FDEF68BE-57D5-4DA6-9CC1-4500A58D9D90",
    "exportFormats": [
    ],
    "includedLayerIds": [
    ],
    "layerOptions": 0,
    "shouldTrim": false
  },
  "fillReplacesImage": false,
  "frame": {
    "_class": "rect",
    "constrainProportions": true,
    "do_objectID": "7B3A9EE6-9BBF-4FE4-9D82-6975D47F461C",
    "height": 510,
    "width": 742,
    "x": 0,
    "y": 0
  },
  "hasClippingMask": false,
  "image": {
    "_class": "MSJSONFileReference",
    "_ref": "images/e8821fa28c2a257f913b64b9cad4b8a85792fd34.png",
    "_ref_class": "MSImageData"
  },
  "intendedDPI": 0,
  "isFixedToViewport": false,
  "isFlippedHorizontal": false,
  "isFlippedVertical": false,
  "isLocked": false,
  "isVisible": true,
  "layerListExpandedType": 0,
  "name": "Shadow",
  "nameIsFixed": false,
  "resizingConstraint": 63,
  "resizingType": 0,
  "rotation": 0,
  "shouldBreakMaskChain": false,
  "style": {
    "_class": "style",
    "blur": {
      "_class": "blur",
      "center": "{0.5, 0.5}",
      "do_objectID": "940DDE9C-E6A4-4199-BFF7-F6553C4469F1",
      "isEnabled": false,
      "motionAngle": 0,
      "radius": 2.5,
      "saturation": 1,
      "type": 0
    },
    "contextSettings": {
      "_class": "graphicsContextSettings",
      "blendMode": 2,
      "do_objectID": "B4881AC8-9CD1-4A95-8933-B7A4C50D4288",
      "opacity": 1
    },
    "do_objectID": "2B47854E-6440-4946-A88F-A7C6E8FD9017",
    "endMarkerType": 0,
    "miterLimit": 10,
    "startMarkerType": 0,
    "windingRule": 1
  }
}