{
  "_class": "shapeGroup",
  "booleanOperation": -1,
  "clippingMaskMode": 0,
  "do_objectID": "086DE331-7A08-4C8D-8712-917545155B25",
  "exportOptions": {
    "_class": "exportOptions",
    "do_objectID": "67331BCF-3CB8-4980-AF3B-1624A853B366",
    "exportFormats": [
    ],
    "includedLayerIds": [
    ],
    "layerOptions": 0,
    "shouldTrim": false
  },
  "frame": {
    "_class": "rect",
    "constrainProportions": true,
    "do_objectID": "3BF39EAF-0228-4CC7-880D-5BF761C92F81",
    "height": 6,
    "width": 6,
    "x": 5.644628099173559,
    "y": 5.5
  },
  "hasClickThrough": false,
  "hasClippingMask": false,
  "isFixedToViewport": false,
  "isFlippedHorizontal": false,
  "isFlippedVertical": false,
  "isLocked": false,
  "isVisible": true,
  "layerListExpandedType": 0,
  "layers": [
    {
      "class": "shapePath",
      "id": "E4CCA915-6084-4721-8442-0DF22B3E0F2A"
    }
  ],
  "name": "Path",
  "nameIsFixed": false,
  "resizingConstraint": 63,
  "resizingType": 0,
  "rotation": 0,
  "shouldBreakMaskChain": false,
  "style": {
    "_class": "style",
    "blur": {
      "_class": "blur",
      "center": "{0.5, 0.5}",
      "do_objectID": "F91318DC-86FC-4863-ABC1-B6CCB2B48CD0",
      "isEnabled": false,
      "motionAngle": 0,
      "radius": 5,
      "type": 0
    },
    "do_objectID": "22D711FA-FD3B-4CDA-91A7-A192F4D2EF46",
    "endMarkerType": 0,
    "fills": [
      {
        "_class": "fill",
        "color": {
          "_class": "color",
          "alpha": 1,
          "blue": 1,
          "green": 1,
          "red": 1
        },
        "fillType": 0,
        "isEnabled": true,
        "noiseIndex": 0,
        "noiseIntensity": 0,
        "patternFillType": 0,
        "patternTileScale": 1
      }
    ],
    "miterLimit": 10,
    "startMarkerType": 0,
    "windingRule": 1
  },
  "windingRule": 1
}