{
  "_class": "symbolInstance",
  "do_objectID": "6E60BDF4-6473-471A-99DA-278FAA8F3930",
  "exportOptions": {
    "_class": "exportOptions",
    "do_objectID": "BE86ED2D-FF95-4EEB-A724-55381E26A178",
    "exportFormats": [
    ],
    "includedLayerIds": [
    ],
    "layerOptions": 0,
    "shouldTrim": false
  },
  "frame": {
    "_class": "rect",
    "constrainProportions": true,
    "do_objectID": "F02B1288-55B8-4573-BA7E-6D127FEB38B6",
    "height": 24,
    "width": 360,
    "x": 0,
    "y": 0
  },
  "horizontalSpacing": 0,
  "isFlippedHorizontal": false,
  "isFlippedVertical": false,
  "isLocked": false,
  "isVisible": true,
  "layerListExpandedType": 0,
  "name": "status bar",
  "nameIsFixed": true,
  "overrideValues": [
  ],
  "resizingConstraint": 63,
  "resizingType": 0,
  "rotation": 0,
  "scale": 1,
  "shouldBreakMaskChain": false,
  "style": {
    "_class": "style",
    "do_objectID": "C5957C4D-87D4-4122-AB31-6459A59DC548",
    "endDecorationType": 0,
    "miterLimit": 10,
    "startDecorationType": 0
  },
  "symbolID": "E2F5171B-3D5C-4ECF-842F-61E2E4976D37",
  "verticalSpacing": 0
}