{
  "_class": "symbolInstance",
  "do_objectID": "60B91D33-EB2E-41CE-978C-9F7900DAF270",
  "exportOptions": {
    "_class": "exportOptions",
    "do_objectID": "6D843242-BC5A-4C19-9985-D7543BABB31F",
    "exportFormats": [
    ],
    "includedLayerIds": [
    ],
    "layerOptions": 0,
    "shouldTrim": false
  },
  "frame": {
    "_class": "rect",
    "constrainProportions": false,
    "do_objectID": "FC71C7A0-1821-4136-98B0-3DC81414B1D1",
    "height": 1,
    "width": 360,
    "x": 0,
    "y": 0
  },
  "horizontalSpacing": 0,
  "isFlippedHorizontal": false,
  "isFlippedVertical": false,
  "isLocked": false,
  "isVisible": true,
  "layerListExpandedType": 0,
  "name": "line",
  "nameIsFixed": false,
  "overrideValues": [
  ],
  "resizingConstraint": 63,
  "resizingType": 0,
  "rotation": 0,
  "scale": 1,
  "shouldBreakMaskChain": false,
  "style": {
    "_class": "style",
    "do_objectID": "4D003206-D373-47D1-9F0C-88BDD09A9A37",
    "endDecorationType": 0,
    "miterLimit": 10,
    "startDecorationType": 0
  },
  "symbolID": "74108322-45E7-4B53-94BE-A936C53C940F",
  "verticalSpacing": 0
}