{
  "_class": "group",
  "booleanOperation": 0,
  "clippingMaskMode": 0,
  "do_objectID": "AAD256F3-86C2-410C-BE33-839AA02346CF",
  "exportOptions": {
    "_class": "exportOptions",
    "do_objectID": "63F47702-3715-4398-AC87-7B0AC1FD0450",
    "exportFormats": [
    ],
    "includedLayerIds": [
    ],
    "layerOptions": 0,
    "shouldTrim": false
  },
  "frame": {
    "_class": "rect",
    "constrainProportions": false,
    "do_objectID": "F275980E-FA95-473E-86F6-9C734E2C0686",
    "height": 30.5,
    "width": 44.5,
    "x": 859.5,
    "y": 435
  },
  "hasClickThrough": false,
  "hasClippingMask": false,
  "isFixedToViewport": false,
  "isFlippedHorizontal": false,
  "isFlippedVertical": false,
  "isLocked": false,
  "isVisible": true,
  "layerListExpandedType": 0,
  "layers": [
    {
      "class": "shapePath",
      "id": "DAF75C36-B2EF-4659-9C1B-BA4D1795FB38"
    },
    {
      "class": "shapePath",
      "id": "588149E8-A5FA-4B5C-8B78-3799602A57BD"
    }
  ],
  "name": "Lightning Connector",
  "nameIsFixed": true,
  "resizingConstraint": 63,
  "resizingType": 0,
  "rotation": 0,
  "shouldBreakMaskChain": false,
  "style": {
    "_class": "style",
    "blur": {
      "_class": "blur",
      "center": "{0.5, 0.5}",
      "do_objectID": "24F1F4F9-9671-4A0C-8759-A1302FC10C2D",
      "isEnabled": false,
      "motionAngle": 0,
      "radius": 5,
      "saturation": 1,
      "type": 0
    },
    "do_objectID": "3128F2DC-FE80-45D2-9D65-4FA86CF36A52",
    "endMarkerType": 0,
    "miterLimit": 10,
    "startMarkerType": 0,
    "windingRule": 1
  }
}